nest_list_print
