Metadata-Version: 2.1
Name: nest-list-print
Version: 1.0.5
Summary: A simple printer of nested lists
Home-page: http://www.headfirstlabs.com
Author: Wancheng Zhou
Author-email: wancheng2012@gmail.com
License: MIT
Platform: UNKNOWN
